LICENSE
MANIFEST.in
README.rst
setup.py
CALLHORIZONS.egg-info/PKG-INFO
CALLHORIZONS.egg-info/SOURCES.txt
CALLHORIZONS.egg-info/dependency_links.txt
CALLHORIZONS.egg-info/top_level.txt
callhorizons/__init__.py
callhorizons/callhorizons.py
doc/Makefile
doc/callhorizons.rst
doc/conf.py
doc/examples.rst
doc/index.rst
doc/install.rst
doc/make.bat
doc/modules.rst
doc/use.rst
doc/_static/.empty