Metadata-Version: 1.1
Name: CALLHORIZONS
Version: 1.1
Summary: CALLHORIZONS is a Python interface to access JPL HORIZONS ephemerides and orbital elements of Solar System bodies.
Home-page: https://github.com/mommermi/callhorizons
Author: Michael Mommert
Author-email: michael.mommert@nau.edu
License: MIT
Keywords: solar system,ephemerides,ephemeris,orbital elements,pyephem,asteroids,planets,spacecraft
Platform: UNKNOWN
Classifier: Development Status :: 5 - Production/Stable
Classifier: Intended Audience :: Science/Research
Classifier: License :: OSI Approved :: MIT License
Classifier: Natural Language :: English
Classifier: Operating System :: OS Independent
Classifier: Programming Language :: Python
Classifier: Topic :: Scientific/Engineering :: Astronomy
Requires: numpy
